ndc_sdk_python/__init__.py
ndc_sdk_python/connector.py
ndc_sdk_python/errors.py
ndc_sdk_python/function_connector.py
ndc_sdk_python/instrumentation.py
ndc_sdk_python/main.py
ndc_sdk_python/models.py
ndc_sdk_python/server.py
ndc_sdk_python-0.42.0.dist-info/WHEEL
ndc_sdk_python-0.42.0.dist-info/entry_points.txt
ndc_sdk_python-0.42.0.dist-info/METADATA
ndc_sdk_python-0.42.0.dist-info/RECORD
