Metadata-Version: 2.3
Name: ndc-sdk-python
Version: 0.42.0
Summary: A Python SDK for creating Hasura Native Data Connectors as per the NDC spec
Author: Daniel Harvey
Author-email: Daniel Harvey <dan.harvey@hasura.io>
Requires-Dist: pydantic>=2.7.0,<3.0.0
Requires-Dist: typing-extensions>=4.11.0,<5.0.0
Requires-Dist: fastapi>=0.110.2
Requires-Dist: uvicorn>=0.29.0
Requires-Dist: opentelemetry-api>=1.20.0,<2.0.0
Requires-Dist: opentelemetry-exporter-otlp>=1.20.0,<2.0.0
Requires-Dist: opentelemetry-instrumentation-fastapi>=0.44b0
Requires-Dist: opentelemetry-instrumentation-logging>=0.44b0
Requires-Dist: opentelemetry-instrumentation-requests>=0.44b0
Requires-Dist: opentelemetry-propagator-b3>=1.20.0,<2.0.0
Requires-Python: >=3.12
